{
    "name": "vim.filetype.mapping",
    "documentation": [
        "```lua",
        "(alias) vim.filetype.mapping Expand to table\u003cstring, string|[string|fun(path: string, bufnr: integer, ...any):string?, fun(b: integer)?, { priority: number }]|fun(path: string, bufnr: integer, ...any):string?, fun(b: integer)?\u003e",
        "```"
    ],
    "meta": [],
    "type": {
        "fields": [],
        "indexes": [
            {
                "key": {
                    "kind": "builtin",
                    "value": "string"
                },
                "value": {
                    "kind": "typereference",
                    "value": "vim.filetype.mapping.value"
                }
            }
        ],
        "kind": "table",
        "name": ""
    }
}