{
    "name": "vim.api.keyset.user_command",
    "documentation": [
        "```lua",
        "(class) vim.api.keyset.user_command",
        "```"
    ],
    "meta": [],
    "type": {
        "fields": [
            {
                "name": "addr",
                "documentation": [
                    "```lua",
                    "(field) vim.api.keyset.user_command.addr: any",
                    "```"
                ],
                "meta": [],
                "type": {
                    "kind": "optional",
                    "type": {
                        "kind": "builtin",
                        "value": "any"
                    }
                }
            },
            {
                "name": "bang",
                "documentation": [
                    "```lua",
                    "(field) vim.api.keyset.user_command.bang: boolean?",
                    "```"
                ],
                "meta": [],
                "type": {
                    "kind": "optional",
                    "type": {
                        "kind": "builtin",
                        "value": "boolean"
                    }
                }
            },
            {
                "name": "bar",
                "documentation": [
                    "```lua",
                    "(field) vim.api.keyset.user_command.bar: boolean?",
                    "```"
                ],
                "meta": [],
                "type": {
                    "kind": "optional",
                    "type": {
                        "kind": "builtin",
                        "value": "boolean"
                    }
                }
            },
            {
                "name": "complete",
                "documentation": [
                    "```lua",
                    "(field) vim.api.keyset.user_command.complete: any",
                    "```"
                ],
                "meta": [],
                "type": {
                    "kind": "optional",
                    "type": {
                        "kind": "builtin",
                        "value": "any"
                    }
                }
            },
            {
                "name": "count",
                "documentation": [
                    "```lua",
                    "(field) vim.api.keyset.user_command.count: any",
                    "```"
                ],
                "meta": [],
                "type": {
                    "kind": "optional",
                    "type": {
                        "kind": "builtin",
                        "value": "any"
                    }
                }
            },
            {
                "name": "desc",
                "documentation": [
                    "```lua",
                    "(field) vim.api.keyset.user_command.desc: any",
                    "```"
                ],
                "meta": [],
                "type": {
                    "kind": "optional",
                    "type": {
                        "kind": "builtin",
                        "value": "any"
                    }
                }
            },
            {
                "name": "force",
                "documentation": [
                    "```lua",
                    "(field) vim.api.keyset.user_command.force: boolean?",
                    "```"
                ],
                "meta": [],
                "type": {
                    "kind": "optional",
                    "type": {
                        "kind": "builtin",
                        "value": "boolean"
                    }
                }
            },
            {
                "name": "keepscript",
                "documentation": [
                    "```lua",
                    "(field) vim.api.keyset.user_command.keepscript: boolean?",
                    "```"
                ],
                "meta": [],
                "type": {
                    "kind": "optional",
                    "type": {
                        "kind": "builtin",
                        "value": "boolean"
                    }
                }
            },
            {
                "name": "nargs",
                "documentation": [
                    "```lua",
                    "(field) vim.api.keyset.user_command.nargs: any",
                    "```"
                ],
                "meta": [],
                "type": {
                    "kind": "optional",
                    "type": {
                        "kind": "builtin",
                        "value": "any"
                    }
                }
            },
            {
                "name": "preview",
                "documentation": [
                    "```lua",
                    "(field) vim.api.keyset.user_command.preview: any",
                    "```"
                ],
                "meta": [],
                "type": {
                    "kind": "optional",
                    "type": {
                        "kind": "builtin",
                        "value": "any"
                    }
                }
            },
            {
                "name": "range",
                "documentation": [
                    "```lua",
                    "(field) vim.api.keyset.user_command.range: any",
                    "```"
                ],
                "meta": [],
                "type": {
                    "kind": "optional",
                    "type": {
                        "kind": "builtin",
                        "value": "any"
                    }
                }
            },
            {
                "name": "register",
                "documentation": [
                    "```lua",
                    "(field) vim.api.keyset.user_command.register: boolean?",
                    "```"
                ],
                "meta": [],
                "type": {
                    "kind": "optional",
                    "type": {
                        "kind": "builtin",
                        "value": "boolean"
                    }
                }
            }
        ],
        "indexes": [],
        "kind": "table",
        "name": "vim.api.keyset.user_command"
    }
}