{
    "name": "vim.api.keyset.cmd_opts",
    "documentation": [
        "```lua",
        "(class) vim.api.keyset.cmd_opts",
        "```"
    ],
    "meta": [],
    "type": {
        "fields": [
            {
                "name": "output",
                "documentation": [
                    "```lua",
                    "(field) vim.api.keyset.cmd_opts.output: boolean?",
                    "```"
                ],
                "meta": [
                    "static"
                ],
                "type": {
                    "kind": "optional",
                    "type": {
                        "kind": "builtin",
                        "value": "boolean"
                    }
                }
            }
        ],
        "indexes": [],
        "kind": "table",
        "name": "vim.api.keyset.cmd_opts"
    }
}